{
    "description": "",
    "tags": [],
    "size": {
        "height": 185,
        "width": 174
    },
    "objects": [
        {
            "id": 1436183631,
            "classId": 11919089,
            "description": "",
            "geometryType": "rectangle",
            "labelerLogin": "Danbus1337",
            "createdAt": "2023-10-12T06:42:53.158Z",
            "updatedAt": "2023-10-12T06:42:53.158Z",
            "tags": [],
            "classTitle": "Selena Gomez",
            "points": {
                "exterior": [
                    [
                        11,
                        7
                    ],
                    [
                        138,
                        162
                    ]
                ],
                "interior": []
            }
        }
    ]
}